requests_logger/__init__.py
requests_logger/common.py
requests_logger/requests_logger.py
requests_logger-0.2.0.dist-info/top_level.txt
requests_logger-0.2.0.dist-info/METADATA
requests_logger-0.2.0.dist-info/DESCRIPTION.rst
requests_logger-0.2.0.dist-info/metadata.json
requests_logger-0.2.0.dist-info/WHEEL
requests_logger-0.2.0.dist-info/RECORD
