Metadata-Version: 2.0
Name: requests-logger
Version: 0.2.0
Summary: Wrapper around Requests to add logging
Home-page: https://github.com/mdmedley/requests_logger
Author: Marcus Medley
Author-email: mdmeds@gmail.com
License: Copyright 2016-2017 Marcus Medley
